htmlparse/__init__.py
htmlparse/html.py
parser_html-1.0.1.dist-info/LICENSE
parser_html-1.0.1.dist-info/METADATA
parser_html-1.0.1.dist-info/WHEEL
parser_html-1.0.1.dist-info/top_level.txt
parser_html-1.0.1.dist-info/RECORD
