Metadata-Version: 2.1
Name: parser-html
Version: 1.0.1
Summary: A basic HTML parser in Python
Author-email: Aarav Malani <aarav.malani@gmail.com>
Project-URL: Homepage, https://github.com/AaravMalani/htmlparse
Project-URL: Bug Tracker, https://github.com/AaravMalani/htmlparse/issues
Classifier: Programming Language :: Python :: 3
Classifier: License :: OSI Approved :: MIT License
Classifier: Operating System :: OS Independent
Requires-Python: >=3.6
License-File: LICENSE
